Metadata-Version: 1.1
Name: todotxtio
Version: 0.2.3
Summary: A simple Python module to parse, manipulate and write Todo.txt data
Home-page: https://github.com/EpocDotFr/todotxtio
Author: Maxime "Epoc" G.
Author-email: contact.nospam@epoc.nospam.fr
License: DBAD
Download-URL: https://github.com/EpocDotFr/todotxtio/archive/todotxtio-0.2.3.tar.gz
Keywords: todotxt todo.txt file parse parser read reader
Platform: UNKNOWN
Classifier: Development Status :: 4 - Beta
Classifier: Intended Audience :: Developers
Classifier: Topic :: Software Development :: Libraries
Classifier: Programming Language :: Python
Classifier: Programming Language :: Python :: 3
Classifier: Operating System :: OS Independent
